pyarxaas/__init__.py
pyarxaas/arxaas.py
pyarxaas/arxaas_connector.py
pyarxaas/converters.py
pyarxaas/privacy_models.py
pyarxaas/state_printer.py
pyarxaas/hierarchy/__init__.py
pyarxaas/hierarchy/date_hierarchy_builder.py
pyarxaas/hierarchy/grouping_based_hierarchy.py
pyarxaas/hierarchy/level.py
pyarxaas/hierarchy/redaction_hierarchy_builder.py
pyarxaas/hierarchy/interval_builder/__init__.py
pyarxaas/hierarchy/interval_builder/interval.py
pyarxaas/hierarchy/interval_builder/interval_hierarchy_builder.py
pyarxaas/hierarchy/order_builder/__init__.py
pyarxaas/hierarchy/order_builder/order_hierarchy_builder.py
pyarxaas/models/__init__.py
pyarxaas/models/anonymization_metrics.py
pyarxaas/models/anonymize_result.py
pyarxaas/models/attribute_type.py
pyarxaas/models/request_builder.py
pyarxaas/models/risk_profile.py
pyarxaas/models/dataset/__init__.py
pyarxaas/models/dataset/attribute.py
pyarxaas/models/dataset/data.py
pyarxaas/models/dataset/dataset.py
tests/pyarxaas/__init__.py
tests/pyarxaas/data_generator.py
tests/pyarxaas/test_ARXaaS.py
tests/pyarxaas/test_AaaSConnector.py
tests/pyarxaas/test_converters.py
tests/pyarxaas/test_request_builder.py
tests/pyarxaas/test_state_printer.py
tests/pyarxaas/hierarchy/__init__.py
tests/pyarxaas/hierarchy/test_DateHierarchyBuilder.py
tests/pyarxaas/hierarchy/test_Interval.py
tests/pyarxaas/hierarchy/test_IntervalHierarchyBuilder.py
tests/pyarxaas/hierarchy/test_OrderHierarchyBuilder.py
tests/pyarxaas/hierarchy/test_ReductionHierarchyBuilder.py
tests/pyarxaas/models/__init__.py
tests/pyarxaas/models/test_AnonymizationMetrics.py
tests/pyarxaas/models/test_AnonymizationResult.py
tests/pyarxaas/models/test_AnonymizeResult.py
tests/pyarxaas/models/test_Attribute.py
tests/pyarxaas/models/test_Data.py
tests/pyarxaas/models/test_Dataset.py
tests/pyarxaas/models/test_RiskProfile.py
tests/pyarxaas/models/test_privacy_models_Tcloseness.py
tests/pyarxaas/models/test_privacy_models_ldiversity.py
pypyARXaaS-0.0.1.dist-info/LICENSE
pypyARXaaS-0.0.1.dist-info/METADATA
pypyARXaaS-0.0.1.dist-info/WHEEL
pypyARXaaS-0.0.1.dist-info/top_level.txt
pypyARXaaS-0.0.1.dist-info/RECORD
